catalogue_service_client/__init__.py
catalogue_service_client/client.py
eev_catalogue_service_client-0.0.3.dist-info/METADATA
eev_catalogue_service_client-0.0.3.dist-info/WHEEL
eev_catalogue_service_client-0.0.3.dist-info/top_level.txt
eev_catalogue_service_client-0.0.3.dist-info/RECORD
