Metadata-Version: 2.1
Name: eev-catalogue-service-client
Version: 0.0.3
Summary: Catalogue service client
Author: EEVend
Author-email: info@eevend.gmail.com
License: UNKNOWN
Platform: UNKNOWN
Requires-Python: >=3.6
Requires-Dist: requests
Requires-Dist: eevend-libs
